scrapyng/__init__.py
scrapyng/fb.py
scrapyng/tables.py
scrapyng/util.py
scrapyng/yboss.py
scrapyng/misc/__init__.py
scrapyng/misc/amazon.py
scrapyng-0.0.3.dist-info/LICENSE
scrapyng-0.0.3.dist-info/METADATA
scrapyng-0.0.3.dist-info/WHEEL
scrapyng-0.0.3.dist-info/top_level.txt
scrapyng-0.0.3.dist-info/RECORD
